psipher.py
psipher-0.0.1.dist-info/LICENSE.txt
psipher-0.0.1.dist-info/METADATA
psipher-0.0.1.dist-info/WHEEL
psipher-0.0.1.dist-info/top_level.txt
psipher-0.0.1.dist-info/RECORD
